qwebsite/__init__.py
qwebsite/__main__.py
qwebsite/base.py
qwebsite/flags.py
qwebsite/run.py
qwebsite/submethod/__init__.py
qwebsite/submethod/github.py
QWebSite-1.0.dist-info/LICENSE
QWebSite-1.0.dist-info/METADATA
QWebSite-1.0.dist-info/WHEEL
QWebSite-1.0.dist-info/entry_points.txt
QWebSite-1.0.dist-info/top_level.txt
QWebSite-1.0.dist-info/RECORD
