Metadata-Version: 2.1
Name: QWebSite
Version: 1.0
Summary: QWebSite
Home-page: https://github.com/QPT-Family/QWebSiteOptimizer
Author: GT-ZhangAcer
Author-email: zhangacer@foxmail.com
License: LGPL
Platform: UNKNOWN
Requires-Python: >3.5
License-File: LICENSE
Requires-Dist: click
Requires-Dist: qgui
Requires-Dist: requests
